autoscraper/__init__.py
autoscraper/auto_scraper.py
autoscraper/utils.py
autoscraper-1.1.14.dist-info/LICENSE
autoscraper-1.1.14.dist-info/METADATA
autoscraper-1.1.14.dist-info/WHEEL
autoscraper-1.1.14.dist-info/top_level.txt
autoscraper-1.1.14.dist-info/RECORD
