Metadata-Version: 2.1
Name: autoscraper
Version: 1.1.14
Summary: A Smart, Automatic, Fast and Lightweight Web Scraper for Python
Home-page: https://github.com/alirezamika/autoscraper
Author: Alireza Mika
Author-email: alirezamika@gmail.com
License: MIT
Keywords: scraping - scraper
Platform: UNKNOWN
Classifier: Development Status :: 4 - Beta
Classifier: License :: OSI Approved :: MIT License
Classifier: Programming Language :: Python :: 3
Requires-Python: >=3.6
License-File: LICENSE
